data_clean_build_helper/__init__.py
data_clean_build_helper/cleaning.py
data_clean_build_helper/etl.py
data_clean_build_helper/sql_builder.py
data_clean_build_helper-0.0.1.dist-info/licenses/LICENSE
tests/__init__.py
tests/test_cleaning.py
tests/test_etl.py
tests/test_sql_builder.py
data_clean_build_helper-0.0.1.dist-info/METADATA
data_clean_build_helper-0.0.1.dist-info/WHEEL
data_clean_build_helper-0.0.1.dist-info/top_level.txt
data_clean_build_helper-0.0.1.dist-info/RECORD
