Metadata-Version: 2.4
Name: data-clean-build-helper
Version: 0.0.1
Summary: A helper library for building and managing data pipelines
Home-page: 
Author: Ashok ARC
Author-email: ashok20akc@gmail.com
Classifier: Programming Language :: Python :: 3
Classifier: License :: OSI Approved :: MIT License
Classifier: Operating System :: OS Independent
Requires-Python: >3.6
License-File: LICENSE
Requires-Dist: pandas
Dynamic: author
Dynamic: author-email
Dynamic: classifier
Dynamic: description
Dynamic: description-content-type
Dynamic: license-file
Dynamic: requires-dist
Dynamic: requires-python
Dynamic: summary
